asyncTaskmini/__init__.py
asyncTaskmini/async_queue.py
asyncTaskmini/async_task.py
asyncTaskmini/ayncTaskManager.py
config/__init__.py
config/config.py
config/configTemplate/config.yaml
utils/__init__.py
utils/logs.py
utils/simplebase64.py
utils/simplemd5.py
utils/singletion.py
asyncTaskmini-0.1.1.dist-info/LICENSE
asyncTaskmini-0.1.1.dist-info/METADATA
asyncTaskmini-0.1.1.dist-info/WHEEL
asyncTaskmini-0.1.1.dist-info/top_level.txt
asyncTaskmini-0.1.1.dist-info/RECORD
