Metadata-Version: 2.1
Name: asyncTaskmini
Version: 0.1.1
Summary: Lightweight asynchronous distributed task library
Home-page: https://github.com/pointerStar007/asyncTask
Author: pointer
Author-email: pointerstar007@gmail.com
License: MIT
Classifier: Development Status :: 4 - Beta
Classifier: Intended Audience :: Developers
Classifier: License :: OSI Approved :: MIT License
Classifier: Topic :: Software Development :: Libraries :: Python Modules
Requires-Python: >=3.6
License-File: LICENSE
Requires-Dist: PyYAML
Requires-Dist: schedule
Requires-Dist: colorlog
Requires-Dist: msgpack
Requires-Dist: redis
